tests/__init__.py
tests/test_tllcommon.py
tllcommon/__init__.py
tllcommon-0.1.0.dist-info/DESCRIPTION.rst
tllcommon-0.1.0.dist-info/METADATA
tllcommon-0.1.0.dist-info/metadata.json
tllcommon-0.1.0.dist-info/RECORD
tllcommon-0.1.0.dist-info/top_level.txt
tllcommon-0.1.0.dist-info/WHEEL
