Metadata-Version: 2.0
Name: tllcommon
Version: 0.1.0
Summary: Low-level, reshareable Python code for Timeline Labs projects
Home-page: https://github.com/timelinelabs/tll-common
Author: Chris Goller
Author-email: goller@timelinelabs.com
License: UNKNOWN
Platform: UNKNOWN
Classifier: Development Status :: 2 - Pre-Alpha
Classifier: Programming Language :: Python
Classifier: Programming Language :: Python :: 2
Classifier: Programming Language :: Python :: 2.7
Classifier: Programming Language :: Python :: 3
Classifier: Programming Language :: Python :: 3.3
Classifier: Programming Language :: Python :: 3.4
Requires-Dist: wheel (==0.23.0)
